{
  "project_info": {
    "project_number": "997349516590",
    "firebase_url": "https://t20matches-e68ab-default-rtdb.firebaseio.com",
    "project_id": "t20matches-e68ab",
    "storage_bucket": "t20matches-e68ab.appspot.com"
  },
  "client": [
    {
      "client_info": {
        "mobilesdk_app_id": "1:997349516590:android:a667c1ae672c255e1786bf",
        "android_client_info": {
          "package_name": "com.tbc.uncagedmist.cricketupdates"
        }
      },
      "oauth_client": [
        {
          "client_id": "997349516590-3iothh533fhqlbh2v9mt8puds5vemmvr.apps.googleusercontent.com",
          "client_type": 3
        }
      ],
      "api_key": [
        {
          "current_key": "AIzaSyCtPcTpzWXxPRAVIBzNeRJZOztXvK9qnEc"
        }
      ],
      "services": {
        "appinvite_service": {
          "other_platform_oauth_client": [
            {
              "client_id": "997349516590-3iothh533fhqlbh2v9mt8puds5vemmvr.apps.googleusercontent.com",
              "client_type": 3
            }
          ]
        }
      }
    },
    {
      "client_info": {
        "mobilesdk_app_id": "1:997349516590:android:02e35df6344fde7f1786bf",
        "android_client_info": {
          "package_name": "tbc.uncagedmist.t20matches"
        }
      },
      "oauth_client": [
        {
          "client_id": "997349516590-3iothh533fhqlbh2v9mt8puds5vemmvr.apps.googleusercontent.com",
          "client_type": 3
        }
      ],
      "api_key": [
        {
          "current_key": "AIzaSyCtPcTpzWXxPRAVIBzNeRJZOztXvK9qnEc"
        }
      ],
      "services": {
        "appinvite_service": {
          "other_platform_oauth_client": [
            {
              "client_id": "997349516590-3iothh533fhqlbh2v9mt8puds5vemmvr.apps.googleusercontent.com",
              "client_type": 3
            }
          ]
        }
      }
    }
  ],
  "configuration_version": "1"
}